wassima/__init__.py
wassima/_version.py
wassima/py.typed
wassima/_os/__init__.py
wassima/_os/_embed.py
wassima/_os/_linux.py
wassima/_os/_macos.py
wassima/_os/_windows.py
wassima-2.0.0.dist-info/METADATA
wassima-2.0.0.dist-info/WHEEL
wassima-2.0.0.dist-info/licenses/LICENSE
wassima-2.0.0.dist-info/RECORD
