Metadata-Version: 2.4
Name: wassima
Version: 2.0.0
Summary: Access your OS root certificates with utmost ease
Project-URL: Changelog, https://github.com/jawah/wassima/blob/main/CHANGELOG.md
Project-URL: Documentation, https://wassima.readthedocs.io
Project-URL: Code, https://github.com/jawah/wassima
Project-URL: Issue tracker, https://github.com/jawah/wassima/issues
Author-email: "Ahmed R. TAHRI" <tahri.ahmed@proton.me>
Maintainer-email: "Ahmed R. TAHRI" <tahri.ahmed@proton.me>
License-Expression: MIT
License-File: LICENSE
Keywords: ca,certifi,certificate,https,root ca,ssl,tls,trust,truststore
Classifier: Development Status :: 5 - Production/Stable
Classifier: Intended Audience :: Developers
Classifier: License :: OSI Approved :: MIT License
Classifier: Operating System :: OS Independent
Classifier: Programming Language :: Python :: 3
Classifier: Programming Language :: Python :: 3 :: Only
Classifier: Programming Language :: Python :: 3.7
Classifier: Programming Language :: Python :: 3.8
Classifier: Programming Language :: Python :: 3.9
Classifier: Programming Language :: Python :: 3.10
Classifier: Programming Language :: Python :: 3.11
Classifier: Programming Language :: Python :: 3.12
Classifier: Programming Language :: Python :: 3.13
Classifier: Programming Language :: Python :: 3.14
Classifier: Programming Language :: Python :: Implementation :: CPython
Classifier: Programming Language :: Python :: Implementation :: PyPy
Classifier: Topic :: Internet :: WWW/HTTP
Classifier: Topic :: Software Development :: Libraries
Requires-Python: >=3.7
